{
  "id": 9,
  "jabatan": {
    "nama_jabatan": "KTU ESTATE",
    "tujuan_jabatan": "Melaksanakan dan mengelola seluruh administrasi perkebunan estate untuk memastikan seluruh administrasi perkebunan estate dilakukan sesuai dengan prosedur untuk mendukung pencapaian target perusahaan",
    "uraian_tugas": "Membuat permohonan biaya / permintaan dana bulanan berdasarkan rencana kerja bulanan Afdeling; Melakukan verifikasi dan konsolidasi budget tahunan kebun hasil evaluasi; Mengelola dana kas kecil (petty cash) dan biaya umum; Memeriksa penjurnalan setiap transaksi agar seluruh transaksi estate tersedia di sistem; Memeriksa verifikasi rekap gaji, lembur dan tunjangan karyawan untuk memastikan seluruh gaji karyawan dibayarkan sesuai dengan ketentuan yang berlaku; Dll",
    "umur": null,
    "jenis_kelamin": null,
    "tinggi_badan": null,
    "berat_badan": null,
    "pendidikan": "S1",
    "jurusan": "Akuntansi, Perpajakan",
    "pengalaman": "2 tahun sebagai KTU Estate",
    "bahasa": "Bahasa Inggris",
    "keterampilan": null,
    "lainnya_requirement": "Pelatihan Administrasi Perkebunan Kelapa Sawit",
    "gaji_maksimal": "5.000.000",
    "pertanyaan_skrining": {
      "operasional": {
        "1": "Apa jabatan saat ini?",
        "2": "Apa level jabatan pada tempat kerja terakhir?",
        "3": "Posisi jabatan apa yang menjadi atasan langsung?",
        "4": "Berapa jumlah Karyawan yang menjadi anak buah/bawahan?",
        "5": "Berapa total jumlah Karyawan di Perusahaan terakhir?",
        "6": "Berapa ha luas area kerja saat ini?",
        "7": "Berapa ha luas area kerja terbesar yang pernah ditangani?",
        "8": "Apa saja jenis area yang pernah ditangani?",
        "9": "Jenis area apa yang paling dikuasai?",
        "10": "Apakah memiliki pengalaman menangani Mekanisasi atau Water Management System?",
        "11": "Berapa lama pengalaman menangani Mekanisasi atau Water Management System?",
        "16": "Tuliskan paling banyak 3 (tiga) masalah/konflik sosial yang dihadapi di lingkungan kerja saat ini.",
        "17": "Apa yang dilakukan untuk menghadapi permasalahan sosial tersebut?",
        "18": "Apakah disediakan kendaraan operasional?",
        "19": "Tuliskan jenis kendaraannya. (Isi '-' jika tidak disediakan)"
      },
      "general": {
        "26": "Dimana lokasi kerja saat ini?",
        "27": "Berapa jauh jarak tempuh dari lokasi kerja ke kota terdekat?",
        "28": "Transportasi apa yang dipergunakan menuju kota terdekat (darat/air/udara)?",
        "29": "Dimana lokasi asal domisili?",
        "30": "Silakan pilih salah satu metode kerja administrasi yang digunakan saat ini.",
        "31": "System apa yang dipergunakan?",
        "32": "Berapa nominal gaji pokok yang diterima?",
        "33": "Berapa nominal Take Home Pay (Nett total gaji dan benefit) yang diterima?",
        "34": "Silakan pilih salah satu pada bentuk tunjangan cuti yang diberikan saat ini dan cantumkan jumlahnya untuk tiap item sesuai plafon yang diterima.",
        "35": "Berapa jumlah hari cuti per tahun?",
        "36": "Tuliskan benefit/tunjangan lainnya yang diterima di tempat kerja terakhir dan besarannya.",
        "37": "Siapakah yang menanggung pajak penghasilan pribadi?",
        "38": "Apa saja jenis asuransi kesehatan yang diterima?"
      },
      "pernyataan": {
        "39": "Apakah bersedia penempatan di Kalimantan Tengah?",
        "40": "Apakah bersedia penempatan sesuai kebutuhan Organisasi?",
        "41": "Apakah bersedia Bapak/Ibu dilakukan background and financial checking?",
        "42": "Apakah bersedia melanjutkan proses seleksi jika penawaran pendapatan bersifat gross?",
        "43": "Apakah bersedia melanjutkan proses seleksi jika paket benefit tidak sesuai dengan permintaan dan atau benefit yang sudah diterima?"
      }
    }
  },
  "kandidat": [
    {
      "id": 29,
      "nama_lengkap": "Hamdan",
      "identitas_diri": {
        "umur": 24,
        "jenis_kelamin": "Laki-laki"
      },
      "kondisi_fisik": {
        "tinggi_badan": 170,
        "berat_badan": 50
      },
      "gaji_diharapkan": {
        "gaji": "Rp 4.500.000",
        "recruiter_dapat_nego": "Tidak"
      },
      "bahasa_asing": [
        { "bahasa": "inggirs", "lisan": "Cukup", "tertulis": "Cukup" }
      ],
      "education": {
        "non_formal": "",
        "formal": [
          {
            "pendidikan": "S1",
            "nama": "UIN ANTASARI BANJARMASIN",
            "jurusan": "PERBANKAN SYARIAH"
          }
        ]
      },
      "work_experience": {
        "pengalaman_pekerjaan": [],
        "pengalaman_pekerjaan_di_perusahaan_ini": [],
        "tanggung_jawab": []
      },
      "jawaban_pertanyaan_skrining": {
        "1": "belum ada",
        "2": "Non Staf",
        "3": "belum ada",
        "4": "belum ada",
        "5": "belum ada",
        "6": "belum ada",
        "7": "belum ada",
        "8": "Bibitan",
        "9": "pengelola keuangan",
        "10": "Mekanisasi Kebun",
        "11": "belum ada",
        "16": "belum bekerja",
        "17": "belum pernah",
        "18": "Tidak Disediakan",
        "19": "-",
        "26": "belum bekerja",
        "27": "-",
        "28": "darat",
        "29": "Jl. Mak'jambek Kel. Raja Sebrang, PangkalanBun",
        "30": "Manual dan System",
        "31": "Microsoft Office",
        "32": "-",
        "33": "-",
        "34": "Tiket dan Uang",
        "35": "7",
        "36": "-",
        "37": "Perusahaan",
        "38": "kesehatan",
        "39": "Ya",
        "40": "Ya",
        "41": "Ya",
        "42": "Ya",
        "43": "Ya"
      }
    },
    {
      "id": 41,
      "nama_lengkap": "Khairul Fikri",
      "identitas_diri": {
        "umur": 39,
        "jenis_kelamin": "Laki-laki"
      },
      "gaji_diharapkan": {
        "gaji": "Rp 8.500.000",
        "recruiter_dapat_nego": "Ya"
      },
      "kondisi_fisik": {
        "tinggi_badan": 170,
        "berat_badan": 69
      },
      "bahasa_asing": null,
      "education": {
        "non_formal": "",
        "formal": [
          {
            "pendidikan": "S1",
            "nama": "Universitas Mulawarman",
            "jurusan": "Manjemen Hutan"
          }
        ]
      },
      "work_experience": {
        "pengalaman_pekerjaan": [
          {
            "nama_perusahaan": "PT Harapan Sawit Sejahtera",
            "jabatan": "Staff Humas",
            "tahun_bekerja": "2011-2012",
            "gaji_rp": "3.500.000",
            "alasan_keluar": "Mengundurkan diri",
            "deskripsi_pekerjaan": "Berkoordinasi dengan mill manager tentang masalah sekitar lingkungan pabrik."
          },
          {
            "nama_perusahaan": "PT. Borneo Indosubur",
            "jabatan": "KTU Estate",
            "tahun_bekerja": "2012-2018",
            "gaji_rp": "5.500.000",
            "alasan_keluar": "Mengundurkan diri",
            "deskripsi_pekerjaan": "Mengelola dan bertanggung jawab atas laporan  administrasi,Gudang, Keuangaan, personalia dan Aset Perusahaan"
          },
          {
            "nama_perusahaan": "PT Cahaya Bintang Sawit Sejati",
            "jabatan": "KTU Mill",
            "tahun_bekerja": "2018-2019",
            "gaji_rp": "6.300.000",
            "alasan_keluar": "Mengundurkan Diri",
            "deskripsi_pekerjaan": "Mengelola dan bertanggung jawab atas laporaan administrasi, Gudang, Keuangan, Personalia dan Aset Perusahaan"
          },
          {
            "nama_perusahaan": "CV. Borneo Kusuma Mandiri",
            "jabatan": "Admin Operasional",
            "tahun_bekerja": "2021-2023",
            "gaji_rp": "5.000.000",
            "alasan_keluar": "Habis Kontrak",
            "deskripsi_pekerjaan": "Membuat laporan Manpower, membuat laporaan Progress pekerjaan, membuat pesanan Material bangunan"
          },
          {
            "nama_perusahaan": "PT Kapuas Sawit Sejahtera",
            "jabatan": "KTU Estate",
            "tahun_bekerja": "2024 - sekarang",
            "gaji_rp": "7.500.000",
            "alasan_keluar": "Untuk dapat mengembangkan diri saya",
            "deskripsi_pekerjaan": "Mengelola dan Bertanggung jawab atas laporaan administrasi, gudang, keuangan, personalia dan aset perusahaan"
          }
        ],
        "pengalaman_pekerjaan_di_perusahaan_ini": [],
        "tanggung_jawab": []
      },
      "jawaban_pertanyaan_skrining": {
        "1": "KTU Estate",
        "2": "Supervisor / Asisten Senior",
        "3": "Estate Manager",
        "4": "6",
        "5": "250",
        "6": "1500",
        "7": "1500",
        "8": "0,1,2,3",
        "9": "Area mineral dan gambut",
        "10": "Mekanisasi Kebun",
        "11": "5 Tahun",
        "16": "Tidak ada",
        "17": "Saling berkoordinasi dengan pihak-pihak yang terkait.",
        "18": "Disediakan",
        "19": "Kendaraan roda 2 dan Mobil",
        "26": "Desa Pantai Kec. Kapuas Barat",
        "27": "45 KM ke Kab. Kapuas",
        "28": "Darat",
        "29": "Kab. Paser Kalimantan Timur",
        "30": "Manual",
        "31": "Tidak ada",
        "32": "7.500.000",
        "33": "8.700.000",
        "34": "Tidak diberikan tunjangan cuti",
        "35": "12",
        "36": "Tunjangan makan dan Premi produksi",
        "37": "Perusahaan dan Karyawan",
        "38": "BPJS",
        "39": "Ya",
        "40": "Ya",
        "41": "Ya",
        "42": "Ya",
        "43": "Ya"
      }
    }
  ]
}
